icmp_sniffer/__init__.py
icmp_sniffer/__main__.py
icmp_sniffer/db.py
icmp_sniffer/sniffer.py
icmp_sniffer-0.1.0.dist-info/METADATA
icmp_sniffer-0.1.0.dist-info/WHEEL
icmp_sniffer-0.1.0.dist-info/entry_points.txt
icmp_sniffer-0.1.0.dist-info/top_level.txt
icmp_sniffer-0.1.0.dist-info/RECORD
