Metadata-Version: 2.1
Name: icmp-sniffer
Version: 0.1.0
Summary: Scans ping packages and posts them to mongodb.
Home-page: https://github.com/Paulius11/icmp-sniffer
Author: Paulius
Author-email: UNKNOWN
License: MIT
Platform: UNKNOWN
Classifier: License :: OSI Approved :: MIT License
Classifier: Programming Language :: Python :: 3
Classifier: Programming Language :: Python :: 3.7
Requires-Dist: pymongo
Requires-Dist: scapy
